glider_client/__init__.py
glider_client/command_results.py
glider_client/commands.py
glider_client/glider.py
glider_client/scripts/__init__.py
glider_client/scripts/scan_adc_delay.py
glider_client/scripts/scan_adc_delay_plot.py
glider_client/scripts/stepping_poi.py
glider_client/scripts/stepping_poi_plot.py
glider_client/tests/__init__.py
glider_client/tests/test_glider_client.py
glider_client/utils/__init__.py
glider_client/utils/alparser.py
glider_client/utils/mcu_registers.py
glider_client/utils/ping.py
glider_client/utils/regexps.py
glider_client/utils/ssrv.py
glider_client-2025.9.1.dist-info/AUTHORS
glider_client-2025.9.1.dist-info/METADATA
glider_client-2025.9.1.dist-info/WHEEL
glider_client-2025.9.1.dist-info/entry_points.txt
glider_client-2025.9.1.dist-info/pbr.json
glider_client-2025.9.1.dist-info/top_level.txt
glider_client-2025.9.1.dist-info/RECORD
