Metadata-Version: 2.1
Name: glider-client
Version: 2025.9.1
Author: chiesa
License: Proprietary
Keywords: glider_client
Classifier: Intended Audience :: Developers
Classifier: License :: Other/Proprietary License
Classifier: Natural Language :: English
Classifier: Programming Language :: Python :: 3
License-File: AUTHORS
Requires-Dist: requests
Requires-Dist: matplotlib
Requires-Dist: numpy
Requires-Dist: pydantic
